antconnect/__init__.py
antconnect/api.py
tests/__init__.py
tests/test_ant.py
ANTConnect-2023.15.1.dist-info/LICENSE
ANTConnect-2023.15.1.dist-info/METADATA
ANTConnect-2023.15.1.dist-info/WHEEL
ANTConnect-2023.15.1.dist-info/top_level.txt
ANTConnect-2023.15.1.dist-info/RECORD
