Metadata-Version: 2.1
Name: ANTConnect
Version: 2023.15.1
Summary: Python SDK for ANT Common Data Engineering
Home-page: https://antcde.io
Author: ANT CDE
Author-email: info@antcde.io
Classifier: Programming Language :: Python :: 3
Classifier: License :: OSI Approved :: MIT License
Classifier: Operating System :: OS Independent
Requires-Python: >=3.6
License-File: LICENSE
Requires-Dist: requests
